{"is_source_file": true, "format": "Python", "description": "This is an ASGI configuration file for a Django project, setting up the ASGI application.", "external_files": ["django.core.asgi", "config.settings"], "external_methods": ["django.core.asgi.get_asgi_application"], "published": ["application"], "classes": [], "methods": [{"name": "get_asgi_application", "description": "Function imported from Django to create the ASGI application."}], "calls": ["django.core.asgi.get_asgi_application"], "search-terms": ["ASGI", "django", "asgi.py", "configuration", "application"], "state": 2, "file_id": 16, "knowledge_revision": 37, "git_revision": "e1d422c570dc50a320114393a8537a9c023a290d", "ctags": [{"_type": "tag", "name": "application", "path": "/home/kavia/workspace/code-generation/simple-task-manager-185050-185059/todo_backend/config/asgi.py", "pattern": "/^application = get_asgi_application()$/", "language": "Python", "kind": "variable"}], "hash": "63d5777b090ac063ecd29c3dfa786ba5", "format-version": 4, "code-base-name": "todo_backend", "filename": "todo_backend/config/asgi.py", "fields": [{"name": "application = get_asgi_application()", "scope": "", "scopeKind": "", "description": "unavailable"}], "revision_history": [{"37": "e1d422c570dc50a320114393a8537a9c023a290d"}]}